zenyx/__init__.py
zenyx/args.py
zenyx/console.py
zenyx/pipe.py
zenyx/pyon.py
zenyx/require.py
zenyx/streams.py
zenyx-2.4.1.dist-info/METADATA
zenyx-2.4.1.dist-info/WHEEL
zenyx-2.4.1.dist-info/licenses/LICENSE
zenyx-2.4.1.dist-info/RECORD
