Metadata-Version: 2.3
Name: zenyx
Version: 2.4.1
Summary: A multitool python object notation package
Project-URL: Homepage, https://github.com/zewenn/zenyx
Project-URL: Issues, https://github.com/zewenn/zenyx/issues
Author-email: zewenn <zc.fallens@gamil.com>
License-File: LICENSE
Classifier: License :: OSI Approved :: MIT License
Classifier: Operating System :: OS Independent
Classifier: Programming Language :: Python :: 3
Requires-Python: >=3.7
